README.md
setup.py
face_recognition/__init__.py
face_recognition/config.py
face_recognition/euclidean_classifier.py
face_recognition/face_recognition.py
facenet_face_recognition.egg-info/PKG-INFO
facenet_face_recognition.egg-info/SOURCES.txt
facenet_face_recognition.egg-info/dependency_links.txt
facenet_face_recognition.egg-info/requires.txt
facenet_face_recognition.egg-info/top_level.txt