Metadata-Version: 2.1
Name: facenet-face-recognition
Version: 0.1
Summary: Face Recognition
Home-page: https://github.com/paoloripamonti/face-recognition.git
Author: Paolo Ripamonti
Author-email: paolo.ripamonti93@gmail.com
License: UNKNOWN
Keywords: facenet,opencv,deep learning,machine learning
Platform: UNKNOWN
Classifier: Programming Language :: Python :: 3
Classifier: License :: OSI Approved :: MIT License
Classifier: Operating System :: OS Independent
